molgraph/__init__.py
molgraph/_filter_warnings.py
molgraph/internal.py
molgraph/applications/__init__.py
molgraph/applications/proteomics/__init__.py
molgraph/applications/proteomics/definitions.py
molgraph/applications/proteomics/peptide.py
molgraph/applications/proteomics/peptide_encoders.py
molgraph/applications/proteomics/peptide_layers.py
molgraph/applications/proteomics/peptide_models.py
molgraph/applications/proteomics/data/_aa_index.json
molgraph/applications/proteomics/data/_aa_smiles.json
molgraph/chemistry/__init__.py
molgraph/chemistry/conformer_generator.py
molgraph/chemistry/conformer_utils.py
molgraph/chemistry/encoders.py
molgraph/chemistry/features.py
molgraph/chemistry/molecular_encoders.py
molgraph/chemistry/ops.py
molgraph/chemistry/vis.py
molgraph/chemistry/benchmark/__init__.py
molgraph/chemistry/benchmark/configs.py
molgraph/chemistry/benchmark/datasets.py
molgraph/chemistry/benchmark/splitters.py
molgraph/chemistry/benchmark/tf_records.py
molgraph/layers/__init__.py
molgraph/layers/gnn.py
molgraph/layers/gnn_input.py
molgraph/layers/gnn_input_layer.py
molgraph/layers/gnn_layer.py
molgraph/layers/gnn_ops.py
molgraph/layers/attentional/__init__.py
molgraph/layers/attentional/attentive_fp_conv.py
molgraph/layers/attentional/gat_conv.py
molgraph/layers/attentional/gated_gcn_conv.py
molgraph/layers/attentional/gatv2_conv.py
molgraph/layers/attentional/gmm_conv.py
molgraph/layers/attentional/gt_conv.py
molgraph/layers/convolutional/__init__.py
molgraph/layers/convolutional/gcn_conv.py
molgraph/layers/convolutional/gcnii_conv.py
molgraph/layers/convolutional/gin_conv.py
molgraph/layers/convolutional/graph_sage_conv.py
molgraph/layers/geometric/__init__.py
molgraph/layers/geometric/dtnn_conv.py
molgraph/layers/geometric/gcf_conv.py
molgraph/layers/geometric/radial_basis.py
molgraph/layers/message_passing/__init__.py
molgraph/layers/message_passing/edge_conv.py
molgraph/layers/message_passing/mpnn_conv.py
molgraph-0.10.0.dist-info/licenses/LICENSE
molgraph-0.10.0.dist-info/METADATA
molgraph-0.10.0.dist-info/WHEEL
molgraph-0.10.0.dist-info/top_level.txt
molgraph-0.10.0.dist-info/RECORD
